pycmsisdapswitcher/__init__.py
pycmsisdapswitcher/__main__.py
pycmsisdapswitcher/cache_manager.py
pycmsisdapswitcher/cli_parser.py
pycmsisdapswitcher/dictionaries.py
pycmsisdapswitcher/exit_codes.py
pycmsisdapswitcher/fw_file_fetcher.py
pycmsisdapswitcher/fw_file_loader.py
pycmsisdapswitcher/fw_file_preparer.py
pycmsisdapswitcher/logging.yaml
pycmsisdapswitcher/print_utils.py
pycmsisdapswitcher/switcher_main.py
pycmsisdapswitcher/toolpack_server_downloader.py
pycmsisdapswitcher/libusb/darwin-arm64/libusb-1.0.dylib
pycmsisdapswitcher/libusb/darwin-x86_64/libusb-1.0.dylib
pycmsisdapswitcher/libusb/win32/libusb-1.0.dll
pycmsisdapswitcher/libusb/win64/libusb-1.0.dll
tests/__init__.py
tests/test_nothing.py
pycmsisdapswitcher-1.0.2.14.dist-info/LICENSE.txt
pycmsisdapswitcher-1.0.2.14.dist-info/METADATA
pycmsisdapswitcher-1.0.2.14.dist-info/WHEEL
pycmsisdapswitcher-1.0.2.14.dist-info/entry_points.txt
pycmsisdapswitcher-1.0.2.14.dist-info/top_level.txt
pycmsisdapswitcher-1.0.2.14.dist-info/RECORD
