Metadata-Version: 2.2
Name: pycmsisdapswitcher
Version: 1.0.2.14
Summary: Switches firmware on Microchip PICkit Basic and other Microchip evaluation boards
Author-email: Microchip Technology <support@microchip.com>
License: MIT
Project-URL: Homepage, https://microchip.com
Keywords: Microchip
Classifier: Development Status :: 3 - Alpha
Classifier: Intended Audience :: Developers
Classifier: Topic :: Software Development :: Embedded Systems
Classifier: Programming Language :: Python :: 3
Classifier: Programming Language :: Python :: 3.8
Classifier: Programming Language :: Python :: 3.9
Classifier: Programming Language :: Python :: 3.10
Classifier: Programming Language :: Python :: 3.11
Classifier: Operating System :: Microsoft :: Windows
Classifier: Operating System :: POSIX :: Linux
Classifier: Operating System :: MacOS
Classifier: License :: OSI Approved :: MIT License
Requires-Python: >=3.8
License-File: LICENSE.txt
Requires-Dist: docopt-ng
Requires-Dist: pyusb
Requires-Dist: IntelHex
Requires-Dist: requests
Requires-Dist: packaging
Provides-Extra: dev
Requires-Dist: pylint>=2.15; extra == "dev"
Provides-Extra: test
Requires-Dist: mock; extra == "test"
Requires-Dist: pytest; extra == "test"
Provides-Extra: doc
Requires-Dist: mock; extra == "doc"
Requires-Dist: sphinx; extra == "doc"
